odoo10_addon_shopinvader_sale_communication-10.0.1.0.1-nspkg.pth
odoo/addons/shopinvader_sale_communication/README.rst
odoo/addons/shopinvader_sale_communication/__init__.py
odoo/addons/shopinvader_sale_communication/__manifest__.py
odoo/addons/shopinvader_sale_communication/models/__init__.py
odoo/addons/shopinvader_sale_communication/models/sale_order.py
odoo/addons/shopinvader_sale_communication/readme/CONTRIBUTORS.rst
odoo/addons/shopinvader_sale_communication/readme/DESCRIPTION.rst
odoo/addons/shopinvader_sale_communication/services/__init__.py
odoo/addons/shopinvader_sale_communication/services/abstract_sale.py
odoo/addons/shopinvader_sale_communication/services/cart.py
odoo/addons/shopinvader_sale_communication/static/description/index.html
odoo/addons/shopinvader_sale_communication/tests/__init__.py
odoo/addons/shopinvader_sale_communication/tests/test_cart.py
odoo/addons/shopinvader_sale_communication/tests/test_sale.py
odoo/addons/shopinvader_sale_communication/views/sale_order.xml
odoo10_addon_shopinvader_sale_communication-10.0.1.0.1.dist-info/METADATA
odoo10_addon_shopinvader_sale_communication-10.0.1.0.1.dist-info/WHEEL
odoo10_addon_shopinvader_sale_communication-10.0.1.0.1.dist-info/namespace_packages.txt
odoo10_addon_shopinvader_sale_communication-10.0.1.0.1.dist-info/top_level.txt
odoo10_addon_shopinvader_sale_communication-10.0.1.0.1.dist-info/RECORD
