Metadata-Version: 2.1
Name: odoo10-addon-shopinvader-sale-communication
Version: 10.0.1.0.1
Summary: This module adds information fields for customers and vendors.
Home-page: https://shopinvader.com/
Author: ACSONE SA/NV
License: AGPL-3
Platform: UNKNOWN
Classifier: Programming Language :: Python
Classifier: Framework :: Odoo
Classifier: License :: OSI Approved :: GNU Affero General Public License v3
Requires-Python: ~=2.7
Requires-Dist: odoo10-addon-shopinvader
Requires-Dist: odoo (<10.1dev,>=10.0)
